wsiml/data.py
wsiml/patch.py
wsiml/register.py
wsiml/taesd/__init__.py
wsiml-2.4.1.dist-info/METADATA
wsiml-2.4.1.dist-info/WHEEL
wsiml-2.4.1.dist-info/RECORD
