Metadata-Version: 2.1
Name: wsiml
Version: 2.4.1
Summary: Project to support machine learning on whole slide images. Currently a placeholder in pre-alpha.
Author: S. Joshua Swamidass
Author-email: swamidass@gmail.com
Requires-Python: >=3.9,<4.0
Classifier: Programming Language :: Python :: 3
Classifier: Programming Language :: Python :: 3.9
Classifier: Programming Language :: Python :: 3.10
Classifier: Programming Language :: Python :: 3.11
Requires-Dist: data-science-types (>=0.2.23,<0.3.0)
Requires-Dist: dm-tree (>=0.1.8,<0.2.0)
Requires-Dist: onnxruntime (>=1.18.0,<2.0.0)
Requires-Dist: pooch (>=1.8.2,<2.0.0)
Requires-Dist: tiffslide (>=2.2.0,<3.0.0)
Requires-Dist: tiffslide-xarray (>=0.1,<0.2)
Requires-Dist: xarray (>=2023.9.0,<2024.0.0)
Requires-Dist: xarray-datatree (>=0.0.12,<0.0.13)
